{ "frames": [
   {
    "filename": "player_animation 0.aseprite",
    "frame": { "x": 0, "y": 0, "w": 64, "h": 64 },
    "rotated": false,
    "trimmed": false,
    "spriteSourceSize": { "x": 0, "y": 0, "w": 64, "h": 64 },
    "sourceSize": { "w": 64, "h": 64 },
    "duration": 100
   },
   {
    "filename": "player_animation 1.aseprite",
    "frame": { "x": 64, "y": 0, "w": 64, "h": 64 },
    "rotated": false,
    "trimmed": false,
    "spriteSourceSize": { "x": 0, "y": 0, "w": 64, "h": 64 },
    "sourceSize": { "w": 64, "h": 64 },
    "duration": 100
   },
   {
    "filename": "player_animation 2.aseprite",
    "frame": { "x": 128, "y": 0, "w": 64, "h": 64 },
    "rotated": false,
    "trimmed": false,
    "spriteSourceSize": { "x": 0, "y": 0, "w": 64, "h": 64 },
    "sourceSize": { "w": 64, "h": 64 },
    "duration": 100
   },
   {
    "filename": "player_animation 3.aseprite",
    "frame": { "x": 192, "y": 0, "w": 64, "h": 64 },
    "rotated": false,
    "trimmed": false,
    "spriteSourceSize": { "x": 0, "y": 0, "w": 64, "h": 64 },
    "sourceSize": { "w": 64, "h": 64 },
    "duration": 100
   },
   {
    "filename": "player_animation 4.aseprite",
    "frame": { "x": 256, "y": 0, "w": 64, "h": 64 },
    "rotated": false,
    "trimmed": false,
    "spriteSourceSize": { "x": 0, "y": 0, "w": 64, "h": 64 },
    "sourceSize": { "w": 64, "h": 64 },
    "duration": 150
   },
   {
    "filename": "player_animation 5.aseprite",
    "frame": { "x": 0, "y": 64, "w": 64, "h": 64 },
    "rotated": false,
    "trimmed": false,
    "spriteSourceSize": { "x": 0, "y": 0, "w": 64, "h": 64 },
    "sourceSize": { "w": 64, "h": 64 },
    "duration": 100
   },
   {
    "filename": "player_animation 6.aseprite",
    "frame": { "x": 64, "y": 64, "w": 64, "h": 64 },
    "rotated": false,
    "trimmed": false,
    "spriteSourceSize": { "x": 0, "y": 0, "w": 64, "h": 64 },
    "sourceSize": { "w": 64, "h": 64 },
    "duration": 100
   },
   {
    "filename": "player_animation 7.aseprite",
    "frame": { "x": 128, "y": 64, "w": 64, "h": 64 },
    "rotated": false,
    "trimmed": false,
    "spriteSourceSize": { "x": 0, "y": 0, "w": 64, "h": 64 },
    "sourceSize": { "w": 64, "h": 64 },
    "duration": 150
   },
   {
    "filename": "player_animation 8.aseprite",
    "frame": { "x": 192, "y": 64, "w": 64, "h": 64 },
    "rotated": false,
    "trimmed": false,
    "spriteSourceSize": { "x": 0, "y": 0, "w": 64, "h": 64 },
    "sourceSize": { "w": 64, "h": 64 },
    "duration": 150
   },
   {
    "filename": "player_animation 9.aseprite",
    "frame": { "x": 256, "y": 64, "w": 64, "h": 64 },
    "rotated": false,
    "trimmed": false,
    "spriteSourceSize": { "x": 0, "y": 0, "w": 64, "h": 64 },
    "sourceSize": { "w": 64, "h": 64 },
    "duration": 150
   },
   {
    "filename": "player_animation 10.aseprite",
    "frame": { "x": 0, "y": 128, "w": 64, "h": 64 },
    "rotated": false,
    "trimmed": false,
    "spriteSourceSize": { "x": 0, "y": 0, "w": 64, "h": 64 },
    "sourceSize": { "w": 64, "h": 64 },
    "duration": 150
   },
   {
    "filename": "player_animation 11.aseprite",
    "frame": { "x": 64, "y": 128, "w": 64, "h": 64 },
    "rotated": false,
    "trimmed": false,
    "spriteSourceSize": { "x": 0, "y": 0, "w": 64, "h": 64 },
    "sourceSize": { "w": 64, "h": 64 },
    "duration": 150
   },
   {
    "filename": "player_animation 12.aseprite",
    "frame": { "x": 128, "y": 128, "w": 64, "h": 64 },
    "rotated": false,
    "trimmed": false,
    "spriteSourceSize": { "x": 0, "y": 0, "w": 64, "h": 64 },
    "sourceSize": { "w": 64, "h": 64 },
    "duration": 150
   },
   {
    "filename": "player_animation 13.aseprite",
    "frame": { "x": 192, "y": 128, "w": 64, "h": 64 },
    "rotated": false,
    "trimmed": false,
    "spriteSourceSize": { "x": 0, "y": 0, "w": 64, "h": 64 },
    "sourceSize": { "w": 64, "h": 64 },
    "duration": 150
   },
   {
    "filename": "player_animation 14.aseprite",
    "frame": { "x": 256, "y": 128, "w": 64, "h": 64 },
    "rotated": false,
    "trimmed": false,
    "spriteSourceSize": { "x": 0, "y": 0, "w": 64, "h": 64 },
    "sourceSize": { "w": 64, "h": 64 },
    "duration": 100
   },
   {
    "filename": "player_animation 15.aseprite",
    "frame": { "x": 0, "y": 192, "w": 64, "h": 64 },
    "rotated": false,
    "trimmed": false,
    "spriteSourceSize": { "x": 0, "y": 0, "w": 64, "h": 64 },
    "sourceSize": { "w": 64, "h": 64 },
    "duration": 250
   },
   {
    "filename": "player_animation 16.aseprite",
    "frame": { "x": 64, "y": 192, "w": 64, "h": 64 },
    "rotated": false,
    "trimmed": false,
    "spriteSourceSize": { "x": 0, "y": 0, "w": 64, "h": 64 },
    "sourceSize": { "w": 64, "h": 64 },
    "duration": 100
   },
   {
    "filename": "player_animation 17.aseprite",
    "frame": { "x": 128, "y": 192, "w": 64, "h": 64 },
    "rotated": false,
    "trimmed": false,
    "spriteSourceSize": { "x": 0, "y": 0, "w": 64, "h": 64 },
    "sourceSize": { "w": 64, "h": 64 },
    "duration": 100
   },
   {
    "filename": "player_animation 18.aseprite",
    "frame": { "x": 192, "y": 192, "w": 64, "h": 64 },
    "rotated": false,
    "trimmed": false,
    "spriteSourceSize": { "x": 0, "y": 0, "w": 64, "h": 64 },
    "sourceSize": { "w": 64, "h": 64 },
    "duration": 100
   },
   {
    "filename": "player_animation 19.aseprite",
    "frame": { "x": 256, "y": 192, "w": 64, "h": 64 },
    "rotated": false,
    "trimmed": false,
    "spriteSourceSize": { "x": 0, "y": 0, "w": 64, "h": 64 },
    "sourceSize": { "w": 64, "h": 64 },
    "duration": 100
   },
   {
    "filename": "player_animation 20.aseprite",
    "frame": { "x": 0, "y": 256, "w": 64, "h": 64 },
    "rotated": false,
    "trimmed": false,
    "spriteSourceSize": { "x": 0, "y": 0, "w": 64, "h": 64 },
    "sourceSize": { "w": 64, "h": 64 },
    "duration": 150
   },
   {
    "filename": "player_animation 21.aseprite",
    "frame": { "x": 64, "y": 256, "w": 64, "h": 64 },
    "rotated": false,
    "trimmed": false,
    "spriteSourceSize": { "x": 0, "y": 0, "w": 64, "h": 64 },
    "sourceSize": { "w": 64, "h": 64 },
    "duration": 150
   }
 ],
 "meta": {
  "app": "http://www.aseprite.org/",
  "version": "1.2.25-x64",
  "image": "player.png",
  "format": "RGBA8888",
  "size": { "w": 320, "h": 320 },
  "scale": "1",
  "frameTags": [
   { "name": "Idle-Right", "from": 0, "to": 0, "direction": "forward" },
   { "name": "Run-Right", "from": 1, "to": 7, "direction": "forward" },
   { "name": "Jump-Up-Right", "from": 8, "to": 10, "direction": "forward" },
   { "name": "Jump-Down-Right", "from": 11, "to": 13, "direction": "forward" },
   { "name": "Attack-Right", "from": 14, "to": 17, "direction": "forward" },
   { "name": "Fast-Attack", "from": 18, "to": 21, "direction": "forward" }
  ]
 }
}
